{
  "assets": [
    {
      "content_type": "application/octet-stream",
      "download_url": "https://github.com/Zheng-up/augment-code-z/releases/download/augment-code-z-v0.825.7/augment-code-z-0.825.7.vsix",
      "name": "augment-code-z-0.825.7.vsix",
      "size": 31853243
    }
  ],
  "fetched_at": "2026-04-03T15:47:33Z",
  "html_url": "https://github.com/Zheng-up/augment-code-z/releases/tag/augment-code-z-v0.825.7",
  "published_at": "2026-04-03T07:00:20Z",
  "release_id": 304965141,
  "repository": "Zheng-up/augment-code-z",
  "tag": "augment-code-z-v0.825.7"
}